synpeaks/__init__.py
synpeaks/channel.py
synpeaks-0.0.3.dist-info/LICENSE
synpeaks-0.0.3.dist-info/METADATA
synpeaks-0.0.3.dist-info/WHEEL
synpeaks-0.0.3.dist-info/top_level.txt
synpeaks-0.0.3.dist-info/RECORD
