Metadata-Version: 2.1
Name: synpeaks
Version: 0.0.3
Summary: Time Series Synthesis with Fixed Peaks
Home-page: https://github.com/jon-chun/synpeaks
Author: Jon Chun
Author-email: jonchun@outlook.com
License: UNKNOWN
Project-URL: Bug Tracker, https://github.com/jon-chun/synpeaks/issues
Platform: UNKNOWN
Classifier: Programming Language :: Python :: 3
Classifier: License :: OSI Approved :: MIT License
Classifier: Operating System :: OS Independent
Requires-Python: >=3.6
License-File: LICENSE
